Ativ1/mult_UC.vhd
library ieee;
use ieee.std_logic_1164.all;
use ieee.numeric_bit.all;

entity UnidadeDeControle is
    port (
        clock : in bit;
        start : in bit;
        reset : in bit;
        ready : out bit;
    
        result_and_count_clear: out bit;
        enable_count : out bit;
        PL_Va : out bit;
        PL_Vb : out bit;
        PL_Vresult : out bit;
        calculate : out bit;
        FD_ready : in bit
        
    );
end UnidadeDeControle;
   
architecture UC_arch of UnidadeDeControle is
type state_t is (s_wait, s_init, s_calculate, s_end);
signal current_state, next_state : state_t;
signal internal_ready, internal_calculating : bit;

begin
    ready <= internal_ready;

    state_machine: process(clock)
    begin
        if (reset = '1') then
            current_state <= s_init;
        elsif (rising_edge(clock)) then
            current_state <= next_state;
        end if;
    end process;

    next_state <= s_wait when (current_state = s_end) else
                  s_init when (current_state = s_wait and start = '1') else
                  s_calculate when (current_state = s_init) else
                  s_end when (current_state = s_calculate and FD_ready = '1');

    internal_ready <= '1' when current_state = s_end else '0';
    internal_calculating <= '1' when current_state = s_calculate else '0';

    process (current_state) is 
    begin 
    case current_state is
        when s_wait =>
            enable_count <= '0';
            result_and_count_clear <= '0';
            PL_Va <= '0';
            PL_Vb <= '0';
            PL_Vresult <= '0';
            calculate <= '0';
        when s_init =>
            enable_count <= '0';
            result_and_count_clear <= '1';
            PL_Va <= '1';
            PL_Vb <= '1';
            PL_Vresult <= '0';
            calculate <= '0';
        when s_calculate =>
            enable_count <= '1';
            result_and_count_clear <= '0';
            PL_Va <= '0';
            PL_Vb <= '0';
            PL_Vresult <= '1';
            calculate <= '1';
        when s_end =>
            enable_count <= '0';
            result_and_count_clear <= '0';
            PL_Va <= '0';
            PL_Vb <= '0';
            PL_Vresult <= '0';
            calculate <= '0';
        end case;
    end process;
            
end architecture;

Ativ1/8bitShiftRegister.vhd
library ieee;
use ieee.std_logic_1164.all;
use ieee.numeric_bit.all;

entity ShiftRegister8Bits is
    
    port (clock       : in bit;
          clear       : in bit;
          parallel_load          : in bit;
          parallel_entry          : in bit_vector(7 downto 0);
          serial_entry : in bit;
          partial_result  : out bit_vector(7 downto 0));
    
   end ShiftRegister8Bits;
   
   architecture ShiftRegister8Bits_arch of ShiftRegister8Bits is
    signal current_value : bit_vector (7 downto 0);
    begin
      partial_result <= current_value(7 downto 0);

    process(clock, clear)
    begin
        if (clear = '1') then
            current_value <= "00000000";
        
        elsif (rising_edge(clock)) then
            if (parallel_load = '1') then
                current_value <= parallel_entry;
            end if;
        
        elsif (falling_edge(clock)) then
            current_value(0) <= current_value(1);
            current_value(1) <= current_value(2);
            current_value(2) <= current_value(3);
            current_value(3) <= current_value(4);
            current_value(4) <= current_value(5);
            current_value(5) <= current_value(6);
            current_value(6) <= current_value(7);
            current_value(7) <= serial_entry;
        
        end if;
    end process;
  end architecture;

Ativ1/4bitRegister.vhd
library ieee;
use ieee.std_logic_1164.all;
use ieee.numeric_bit.all;

entity Register4Bits is
    port (clock : in bit;
          clear : in bit;
          load  : in bit;
          entry : in bit_vector(3 downto 0);
          reg   : out bit_vector(3 downto 0));
end entity;

architecture Register4Bits_arch of Register4Bits is
signal current_value : bit_vector(3 downto 0);
begin
    reg <= current_value;
    process(clock, clear)
    begin
        if (clear = '1') then
            current_value <= "0000";
        elsif (rising_edge(clock)) then
            if (load = '1') then
                current_value <= entry;
            end if;
        end if;
    end process;
end architecture;

Ativ1/4bitShiftRegister.vhd
library ieee;
use ieee.std_logic_1164.all;
use ieee.numeric_bit.all;

entity ShiftRegister4Bits is
    
    port (clock       : in bit;
          clear       : in bit;
          parallel_load          : in bit;
          parallel_entry          : in bit_vector(3 downto 0);
          enable_shift : in bit;
          serial_entry : in bit;
          reg_value  : out bit_vector(3 downto 0));
    
   end ShiftRegister4Bits;
   
   architecture ShiftRegister4Bits_arch of ShiftRegister4Bits is
    signal current_value : bit_vector (3 downto 0);
    begin
      reg_value <= current_value(3 downto 0);

    process(clock, clear)
    begin
        if (clear = '1') then
            current_value <= "0000";
        
        elsif (rising_edge(Clock)) then
            if (parallel_load = '1') then
                current_value <= parallel_entry;
            end if;
        
        elsif (falling_edge(clock)) then
            if (enable_shift = '1') then
                current_value(3) <= serial_entry;
                current_value(2) <= current_value(3);
                current_value(1) <= current_value(2);
                current_value(0) <= current_value(1);
            end if;
        end if;
    end process;
  end architecture;

Ativ1/DFlipFlop.vhd
library ieee;
use ieee.std_logic_1164.all;
use ieee.numeric_bit.all;

entity FlipFlopD is
    port (D, clock : in bit;
          Q        : out bit);
end entity;

architecture FlipFlopD_arch of FlipFlopD is
begin
    process(clock)
    begin            
        if (rising_edge(clock)) then Q <= D;
        end if;
    end process;
end architecture;

Ativ1/4bitAdder.vhd
LIBRARY ieee;
USE ieee.std_logic_1164.ALL;
USE ieee.numeric_bit.ALL;

ENTITY Adder4Bits IS
  PORT (
    Va, Vb : IN bit_vector (3 DOWNTO 0);
    Cout : OUT BIT;
    Vresult : OUT bit_vector (3 DOWNTO 0));
END ENTITY;

ARCHITECTURE Adder4Bits_arch OF Adder4Bits IS
  SIGNAL Va_5bits, Vb_5bits, Vresult_5bits : unsigned (4 DOWNTO 0);
BEGIN
  Va_5bits <= unsigned ('0' & Va);
  Vb_5bits <= unsigned ('0' & Vb);
  Vresult_5bits <= Va_5bits + Vb_5bits;
  Vresult <= bit_vector(Vresult_5bits(3 DOWNTO 0));
  Cout <= BIT(Vresult_5bits(4));
END ARCHITECTURE;

Ativ1/3bitCounter.vhd
library ieee;
use ieee.std_logic_1164.all;
use ieee.numeric_bit.all;

entity Counter3Bits is
    port (clock  : in bit;
          clear  : in bit;
          load : in bit;
          entry: in bit_vector(2 downto 0);
          enable_count : in bit;
          RCO : out bit;
          count_variable : out bit_vector(2 downto 0));
end entity;

architecture Counter3Bits_arch of Counter3Bits is
    signal current_count : unsigned(2 downto 0);
    
begin
    count_variable <= bit_vector(current_count);
    RCO <= '1' when current_count = "100" else '0'; -- RCO enables on "100" in order to know when all the 4 bits from "multiplicando" were analyzed 
    process (clock, clear)
    begin
        if (clear = '1') then
            current_count <= "000";
        elsif (rising_edge(clock)) then
            if (load = '1') then
                current_count <= unsigned(entry);
            elsif (enable_count = '1') then
                current_count <= current_count + 1;
            end if;
        end if;
    end process;
end architecture;

Ativ1/mult_FD.vhd
library ieee;
use ieee.std_logic_1164.all;
use ieee.numeric_bit.all;

entity FluxoDeDados is
    port (
        clock : in bit;
        Va : in bit_vector (3 downto 0);
        Vb : in bit_vector (3 downto 0);
        Vresult : out bit_vector (7 downto 0);
        
        result_and_count_clear: in bit;
        enable_count : in bit;
        PL_Va : in bit;
        PL_Vb : in bit;
        PL_Vresult : in bit;
        calculate : in bit;
        FD_ready : out bit
    );
end entity;

architecture FD_arch of FluxoDeDados is 

component Adder4Bits is
    port (Va, Vb  : in bit_vector (3 downto 0);
          Cout    : out bit;
          Vresult : out bit_vector (3 downto 0));
end component;

component Register4Bits is
    port (clock : in bit;
          clear : in bit;
          load  : in bit;
          entry : in bit_vector(3 downto 0);
          reg   : out bit_vector(3 downto 0));
end component;

component ShiftRegister4Bits is
    
    port (clock       : in bit;
          clear       : in bit;
          parallel_load          : in bit;
          parallel_entry          : in bit_vector(3 downto 0);
          enable_shift : in bit;
          serial_entry : in bit;
          reg_value  : out bit_vector(3 downto 0));
    
   end component;

component ShiftRegister8Bits is
    port (clock           : in bit;
          clear           : in bit;
          parallel_load   : in bit;
          parallel_entry  : in bit_vector(7 downto 0);
          serial_entry    : in bit;
          partial_result  : out bit_vector(7 downto 0));
    
   end component;

component Counter3Bits is
    port (clock          : in bit;
          clear          : in bit;
          load           : in bit;
          entry          : in bit_vector(2 downto 0);
          enable_count   : in bit;
          RCO            : out bit;
          count_variable : out bit_vector(2 downto 0));
end component;

component FlipFlopD is
    port (D, clock : in bit;
          Q        : out bit);
end component;

signal ready_FF_out, change_ready, add_cout, counter_RCO, aux_ready, reg_add_cout : bit;
signal counter_variable : bit_vector(2 downto 0);
signal Reg_Va, Reg_Vb, added_parcel, add_result : bit_vector(3 downto 0);
signal Reg_Vresult, Vresult_shifter_entry : bit_vector(7 downto 0); 

begin
    FD_ready <= aux_ready;
    aux_ready <= (not ready_FF_out) and (counter_RCO);
    change_ready <= aux_ready and counter_RCO;
    added_parcel <= Reg_Vb when Reg_Va(0) = '1' else "0000";
    Vresult_shifter_entry <= add_result & Reg_Vresult(3 downto 0); 
    Vresult <= Reg_Vresult;

    ready_FF: FlipFlopD port map (change_ready, clock, ready_FF_out);

    counter: Counter3Bits port map (clock, result_and_count_clear , '0', "000", enable_count, counter_RCO, counter_variable);

    adder: Adder4Bits port map (added_parcel, Reg_Vresult(7 downto 4), add_cout, add_result);
    Carry_out: FlipFlopD port map (add_cout, clock, reg_add_cout);

    Va_shifter: ShiftRegister4Bits port map (clock, '0', PL_Va, Va, calculate, Reg_Va(0), Reg_Va);
    Vb_register: Register4Bits port map (clock, '0', PL_Vb, Vb, Reg_Vb);
    result_shifter: ShiftRegister8Bits port map (clock, result_and_count_clear, PL_Vresult, Vresult_shifter_entry, reg_add_cout, Reg_Vresult);
        
end architecture;

Ativ1/sum_shift_multiplier.vhd
library ieee;
use ieee.numeric_bit.all;

entity multiplicador_modificado is
    port (
      Clock : in bit ;
      Reset : in bit ;
      Start : in bit ;
      Va, Vb : in bit_vector (3 downto 0 ) ;
      Vresult : out bit_vector (7 downto 0 ) ;
      Ready : out bit
    );
end entity;
 
architecture MM_arch of multiplicador_modificado is

    component FluxoDeDados is
        port (
            clock : in bit;
            Va : in bit_vector (3 downto 0);
            Vb : in bit_vector (3 downto 0);
            Vresult : out bit_vector (7 downto 0);
            
            result_and_count_clear: in bit;
            enable_count : in bit;
            PL_Va : in bit;
            PL_Vb : in bit;
            PL_Vresult : in bit;
            calculate : in bit;
            FD_ready : out bit
        );
    end component;
    
    component UnidadeDeControle is
        port (
            clock : in bit;
            start : in bit;
            reset : in bit;
            ready : out bit;
        
            result_and_count_clear: out bit;
            enable_count : out bit;
            PL_Va : out bit;
            PL_Vb : out bit;
            PL_Vresult : out bit;
            calculate : out bit;
            FD_ready : in bit
        );
    end component;

    signal result_and_count_clear, enable_count, PL_Va, PL_Vb, PL_Vresult, calculate, FD_ready, invert_clock : bit;
    begin
        invert_clock <= not clock;
        FD: FluxoDeDados port map (invert_clock, Va, Vb, Vresult, result_and_count_clear, enable_count, PL_Va, PL_Vb, PL_Vresult, calculate, FD_ready);
        UC: UnidadeDeControle port map (clock, start, reset, ready, result_and_count_clear, enable_count, PL_Va, PL_Vb, PL_Vresult, calculate, FD_ready);


end architecture;

Ativ1/ssm_tb.vhd
-------------------------------------------------------
--! @file multiplicador_tb.vhd
--! @brief testbench for synchronous multiplier
--! @author Edson Midorikawa (emidorik@usp.br)
--! @date 2020-06-15
-------------------------------------------------------

library ieee;
use ieee.numeric_bit.all;

entity multiplicador_tb is
end entity;

architecture tb of multiplicador_tb is
  
  -- Componente a ser testado (Device Under Test -- DUT)
  component multiplicador_modificado
    port (
      Clock:    in  bit;
      Reset:    in  bit;
      Start:    in  bit;
      Va, Vb:    in  bit_vector(3 downto 0);
      Vresult:  out bit_vector(7 downto 0);
      Ready:    out bit
    );
  end component;
  
  -- Declaração de sinais para conectar a componente
  signal clk_in: bit := '0';
  signal rst_in, start_in, ready_out: bit := '0';
  signal va_in, vb_in: bit_vector(3 downto 0);
  signal result_out: bit_vector(7 downto 0);

  -- Configurações do clock
  signal keep_simulating: bit := '0'; -- delimita o tempo de geração do clock
  constant clockPeriod : time := 1 ns;
  
begin
  -- Gerador de clock: executa enquanto 'keep_simulating = 1', com o período
  -- especificado. Quando keep_simulating=0, clock é interrompido, bem como a 
  -- simulação de eventos
  clk_in <= (not clk_in) and keep_simulating after clockPeriod/2;
  
  ---- O código abaixo, sem o "keep_simulating", faria com que o clock executasse
  ---- indefinidamente, de modo que a simulação teria que ser interrompida manualmente
  -- clk_in <= (not clk_in) after clockPeriod/2; 
  
  -- Conecta DUT (Device Under Test)
  dut: multiplicador_modificado
       port map(Clock=>   clk_in,
                Reset=>   rst_in,
                Start=>   start_in,
                Va=>      va_in,
                Vb=>      vb_in,
                Vresult=> result_out,
                Ready=>   ready_out
      );

  ---- Gera sinais de estimulo
  stimulus: process is
  begin
  
    assert false report "simulation start" severity note;
    keep_simulating <= '1';
    
    ----------------------------------------------------------------------------------

    ---- Caso de teste 2: A=15, B=11
    Va_in <= "1111"; 
    Vb_in <= "1011"; 
    -- pulso do sinal de Start
    wait until falling_edge(clk_in);
    start_in <= '1';
    wait until falling_edge(clk_in);
    start_in <= '0';
    -- espera pelo termino da multiplicacao
    wait until ready_out='1';
    wait for 1 ps;
    -- verifica resultado
    assert (result_out/="10100101") report "2.OK: 15x11=10100101 (165)" severity note;
    assert false report "result: " & integer'image(to_integer(unsigned(result_out))) severity note;
    
    wait for clockPeriod;    

    ----------------------------------------------------------------------------------

    ---- Caso de teste 3: A=15, B=0
    Va_in <= "1111"; 
    Vb_in <= "0000"; 
    -- pulso do sinal de Start
    wait until falling_edge(clk_in);
    start_in <= '1';
    wait until falling_edge(clk_in);
    start_in <= '0';
    -- espera pelo termino da multiplicacao
    wait until ready_out='1';
    wait for 1 ps;
    -- verifica resultado
    assert (result_out/="00000000") report "3.OK: 15x0=00000000 (0)" severity note;
    assert false report "result: " & integer'image(to_integer(unsigned(result_out))) severity note;

    
    wait for clockPeriod;    
 
    ----------------------------------------------------------------------------------

    ---- Caso de teste 4: A=1, B=11
    Va_in <= "0001"; 
    Vb_in <= "1011"; 
    -- pulso do sinal de Start
    wait until falling_edge(clk_in);
    start_in <= '1';
    wait until falling_edge(clk_in);
    start_in <= '0';
    -- espera pelo termino da multiplicacao
    wait until ready_out='1';
    wait for 1 ps;
    -- verifica resultado
    assert (result_out/="00001011") report "4.OK: 1x11=00001011 (11)" severity note;
    assert false report "result: " & integer'image(to_integer(unsigned(result_out))) severity note;
    
    wait for clockPeriod;  
    ----------------------------------------------------------------------------------

    ---- inserir outros casos de teste aqui

    ----------------------------------------------------------------------------------
 
    -- final do testbench
    assert false report "simulation end" severity note;
    keep_simulating <= '0';
    
    wait; -- fim da simulação: aguarda indefinidamente
  end process;


end architecture;

Ativ1/mult.vcd
$date
  Mon Aug 14 15:00:03 2023
$end
$version
  GHDL v0
$end
$timescale
  1 fs
$end
$scope module standard $end
$upscope $end
$scope module numeric_bit $end
$upscope $end
$scope module std_logic_1164 $end
$upscope $end
$scope module multiplicador_tb $end
$var reg 1 ! clk_in $end
$var reg 1 " rst_in $end
$var reg 1 # start_in $end
$var reg 1 $ ready_out $end
$var reg 4 % va_in[3:0] $end
$var reg 4 & vb_in[3:0] $end
$var reg 8 ' result_out[7:0] $end
$var reg 1 ( keep_simulating $end
$scope module dut $end
$var reg 1 ) clock $end
$var reg 1 * reset $end
$var reg 1 + start $end
$var reg 4 , va[3:0] $end
$var reg 4 - vb[3:0] $end
$var reg 8 . vresult[7:0] $end
$var reg 1 / ready $end
$var reg 1 0 result_and_count_clear $end
$var reg 1 1 enable_count $end
$var reg 1 2 pl_va $end
$var reg 1 3 pl_vb $end
$var reg 1 4 pl_vresult $end
$var reg 1 5 calculate $end
$var reg 1 6 fd_ready $end
$var reg 1 7 invert_clock $end
$scope module fd $end
$var reg 1 8 clock $end
$var reg 4 9 va[3:0] $end
$var reg 4 : vb[3:0] $end
$var reg 8 ; vresult[7:0] $end
$var reg 1 < result_and_count_clear $end
$var reg 1 = enable_count $end
$var reg 1 > pl_va $end
$var reg 1 ? pl_vb $end
$var reg 1 @ pl_vresult $end
$var reg 1 A calculate $end
$var reg 1 B fd_ready $end
$var reg 1 C ready_ff_out $end
$var reg 1 D change_ready $end
$var reg 1 E add_cout $end
$var reg 1 F counter_rco $end
$var reg 1 G aux_ready $end
$var reg 1 H reg_add_cout $end
$var reg 3 I counter_variable[2:0] $end
$var reg 4 J reg_va[3:0] $end
$var reg 4 K reg_vb[3:0] $end
$var reg 4 L added_parcel[3:0] $end
$var reg 4 M add_result[3:0] $end
$var reg 8 N reg_vresult[7:0] $end
$var reg 8 O vresult_shifter_entry[7:0] $end
$scope module ready_ff $end
$var reg 1 P d $end
$var reg 1 Q clock $end
$var reg 1 R q $end
$upscope $end
$scope module counter $end
$var reg 1 S clock $end
$var reg 1 T clear $end
$var reg 1 U load $end
$var reg 3 V entry[2:0] $end
$var reg 1 W enable_count $end
$var reg 1 X rco $end
$var reg 3 Y count_variable[2:0] $end
$var reg 3 Z current_count[2:0] $end
$upscope $end
$scope module adder $end
$var reg 4 [ va[3:0] $end
$var reg 4 \ vb[3:0] $end
$var reg 1 ] cout $end
$var reg 4 ^ vresult[3:0] $end
$var reg 5 _ va_5bits[4:0] $end
$var reg 5 ` vb_5bits[4:0] $end
$var reg 5 a vresult_5bits[4:0] $end
$upscope $end
$scope module carry_out $end
$var reg 1 b d $end
$var reg 1 c clock $end
$var reg 1 d q $end
$upscope $end
$scope module va_shifter $end
$var reg 1 e clock $end
$var reg 1 f clear $end
$var reg 1 g parallel_load $end
$var reg 4 h parallel_entry[3:0] $end
$var reg 1 i enable_shift $end
$var reg 1 j serial_entry $end
$var reg 4 k reg_value[3:0] $end
$var reg 4 l current_value[3:0] $end
$upscope $end
$scope module vb_register $end
$var reg 1 m clock $end
$var reg 1 n clear $end
$var reg 1 o load $end
$var reg 4 p entry[3:0] $end
$var reg 4 q reg[3:0] $end
$var reg 4 r current_value[3:0] $end
$upscope $end
$scope module result_shifter $end
$var reg 1 s clock $end
$var reg 1 t clear $end
$var reg 1 u parallel_load $end
$var reg 8 v parallel_entry[7:0] $end
$var reg 1 w serial_entry $end
$var reg 8 x partial_result[7:0] $end
$var reg 8 y current_value[7:0] $end
$upscope $end
$upscope $end
$scope module uc $end
$var reg 1 z clock $end
$var reg 1 { start $end
$var reg 1 | reset $end
$var reg 1 } ready $end
$var reg 1 !" result_and_count_clear $end
$var reg 1 "" enable_count $end
$var reg 1 #" pl_va $end
$var reg 1 $" pl_vb $end
$var reg 1 %" pl_vresult $end
$var reg 1 &" calculate $end
$var reg 1 '" fd_ready $end
$comment current_state is not handled $end
$comment next_state is not handled $end
$var reg 1 (" internal_ready $end
$var reg 1 )" internal_calculating $end
$upscope $end
$upscope $end
$upscope $end
$enddefinitions $end
#0
0!
0"
0#
0$
b1111 %
b1011 &
b00000000 '
1(
0)
0*
0+
b1111 ,
b1011 -
b00000000 .
0/
00
01
02
03
04
05
06
17
18
b1111 9
b1011 :
b00000000 ;
0<
0=
0>
0?
0@
0A
0B
0C
0D
0E
0F
0G
0H
b000 I
b0000 J
b0000 K
b0000 L
b0000 M
b00000000 N
b00000000 O
0P
1Q
0R
1S
0T
0U
b000 V
0W
0X
b000 Y
b000 Z
b0000 [
b0000 \
0]
b0000 ^
b00000 _
b00000 `
b00000 a
0b
1c
0d
1e
0f
0g
b1111 h
0i
0j
b0000 k
b0000 l
1m
0n
0o
b1011 p
b0000 q
b0000 r
1s
0t
0u
b00000000 v
0w
b00000000 x
b00000000 y
0z
0{
0|
0}
0!"
0""
0#"
0$"
0%"
0&"
0'"
0("
0)"
#500000
1!
1)
07
08
0Q
0S
0c
0e
0m
0s
1z
#1000000
0!
1#
0)
1+
17
18
1Q
1S
1c
1e
1m
1s
0z
1{
#1500000
1!
1)
10
12
13
07
08
1<
1>
1?
0Q
0S
1T
0c
0e
1g
0m
1o
0s
1t
1z
1!"
1#"
1$"
#2000000
0!
0#
0)
0+
17
18
b1111 J
b1011 K
b1011 L
b1011 M
b10110000 O
1Q
1S
b1011 [
b1011 ^
b01011 _
b01011 a
1c
1e
1j
b1111 k
b1111 l
1m
b1011 q
b1011 r
1s
b10110000 v
0z
0{
#2500000
1!
1)
00
11
02
03
14
15
07
08
0<
1=
0>
0?
1@
1A
0Q
0S
0T
1W
0c
0e
0g
1i
0m
0o
0s
0t
1u
1z
0!"
1""
0#"
0$"
1%"
1&"
1)"
#3000000
0!
b10110000 '
0)
b10110000 .
17
18
b10110000 ;
1E
b001 I
b0110 M
b10110000 N
b01100000 O
1Q
1S
b001 Y
b001 Z
b1011 \
1]
b0110 ^
b01011 `
b10110 a
1b
1c
1e
1m
1s
b01100000 v
b10110000 x
b10110000 y
0z
#3500000
1!
b01011000 '
1)
b01011000 .
07
08
b01011000 ;
b0000 M
b01011000 N
b00001000 O
0Q
0S
b0101 \
b0000 ^
b00101 `
b10000 a
0c
0e
0m
0s
b00001000 v
b01011000 x
b01011000 y
1z
#4000000
0!
b00001000 '
0)
b00001000 .
17
18
b00001000 ;
0E
1H
b010 I
b1011 M
b00001000 N
b10111000 O
1Q
1S
b010 Y
b010 Z
b0000 \
0]
b1011 ^
b00000 `
b01011 a
0b
1c
1d
1e
1m
1s
b10111000 v
1w
b00001000 x
b00001000 y
0z
#4500000
1!
b10000100 '
1)
b10000100 .
07
08
b10000100 ;
1E
b0011 M
b10000100 N
b00110100 O
0Q
0S
b1000 \
1]
b0011 ^
b01000 `
b10011 a
1b
0c
0e
0m
0s
b00110100 v
b10000100 x
b10000100 y
1z
#5000000
0!
b00110100 '
0)
b00110100 .
17
18
b00110100 ;
0E
b011 I
b1110 M
b00110100 N
b11100100 O
1Q
1S
b011 Y
b011 Z
b0011 \
0]
b1110 ^
b00011 `
b01110 a
0b
1c
1e
1m
1s
b11100100 v
b00110100 x
b00110100 y
0z
#5500000
1!
b10011010 '
1)
b10011010 .
07
08
b10011010 ;
1E
b0100 M
b10011010 N
b01001010 O
0Q
0S
b1001 \
1]
b0100 ^
b01001 `
b10100 a
1b
0c
0e
0m
0s
b01001010 v
b10011010 x
b10011010 y
1z
#6000000
0!
b01001010 '
0)
b01001010 .
16
17
18
b01001010 ;
1B
1D
0E
1F
1G
b100 I
b1111 M
b01001010 N
b11111010 O
1P
1Q
1S
1X
b100 Y
b100 Z
b0100 \
0]
b1111 ^
b00100 `
b01111 a
0b
1c
1e
1m
1s
b11111010 v
b01001010 x
b01001010 y
0z
1'"
#6500000
1!
1$
b10100101 '
1)
b10100101 .
1/
01
04
05
07
08
b10100101 ;
0=
0@
0A
1E
b0101 M
b10100101 N
b01010101 O
0Q
0S
0W
b1010 \
1]
b0101 ^
b01010 `
b10101 a
1b
0c
0e
0i
0m
0s
0u
b01010101 v
b10100101 x
b10100101 y
1z
1}
0""
0%"
0&"
1("
0)"
#6501000
#7000000
0!
0)
06
17
18
0B
1C
0D
0G
0P
1Q
1R
1S
1c
1e
1m
1s
0z
0'"
#7500000
1!
0$
b11010010 '
1)
b11010010 .
0/
07
08
b11010010 ;
b1000 M
b11010010 N
b10000010 O
0Q
0S
b1101 \
b1000 ^
b01101 `
b11000 a
0c
0e
0m
0s
b10000010 v
b11010010 x
b11010010 y
1z
0}
0("
#7501000
b0000 &
b0000 -
b0000 :
b0000 p
#8000000
0!
1#
0)
1+
16
17
18
1B
0C
1D
1G
1P
1Q
0R
1S
1c
1e
1m
1s
0z
1{
1'"
#8500000
1!
b00000000 '
1)
b00000000 .
10
12
13
06
07
08
b00000000 ;
1<
1>
1?
0B
0D
0E
0F
0G
b000 I
b1011 M
b00000000 N
b10110000 O
0P
0Q
0S
1T
0X
b000 Y
b000 Z
b0000 \
0]
b1011 ^
b00000 `
b01011 a
0b
0c
0e
1g
0m
1o
0s
1t
b10110000 v
b00000000 x
b00000000 y
1z
1!"
1#"
1$"
0'"
#9000000
0!
0#
0)
0+
17
18
0H
b0000 K
b0000 L
b0000 M
b00000000 O
1Q
1S
b0000 [
b0000 ^
b00000 _
b00000 a
1c
0d
1e
1m
b0000 q
b0000 r
1s
b00000000 v
0w
0z
0{
#9500000
1!
1)
00
11
02
03
14
15
07
08
0<
1=
0>
0?
1@
1A
0Q
0S
0T
1W
0c
0e
0g
1i
0m
0o
0s
0t
1u
1z
0!"
1""
0#"
0$"
1%"
1&"
1)"
#10000000
0!
0)
17
18
b001 I
1Q
1S
b001 Y
b001 Z
1c
1e
1m
1s
0z
#10500000
1!
1)
07
08
0Q
0S
0c
0e
0m
0s
1z
#11000000
0!
0)
17
18
b010 I
1Q
1S
b010 Y
b010 Z
1c
1e
1m
1s
0z
#11500000
1!
1)
07
08
0Q
0S
0c
0e
0m
0s
1z
#12000000
0!
0)
17
18
b011 I
1Q
1S
b011 Y
b011 Z
1c
1e
1m
1s
0z
#12500000
1!
1)
07
08
0Q
0S
0c
0e
0m
0s
1z
#13000000
0!
0)
16
17
18
1B
1D
1F
1G
b100 I
1P
1Q
1S
1X
b100 Y
b100 Z
1c
1e
1m
1s
0z
1'"
#13500000
1!
1$
1)
1/
01
04
05
07
08
0=
0@
0A
0Q
0S
0W
0c
0e
0i
0m
0s
0u
1z
1}
0""
0%"
0&"
1("
0)"
#13501000
#14000000
0!
0)
06
17
18
0B
1C
0D
0G
0P
1Q
1R
1S
1c
1e
1m
1s
0z
0'"
#14500000
1!
0$
1)
0/
07
08
0Q
0S
0c
0e
0m
0s
1z
0}
0("
#14501000
b0001 %
b1011 &
b0001 ,
b1011 -
b0001 9
b1011 :
b0001 h
b1011 p
#15000000
0!
1#
0)
1+
16
17
18
1B
0C
1D
1G
1P
1Q
0R
1S
1c
1e
1m
1s
0z
1{
1'"
#15500000
1!
1)
10
12
13
06
07
08
1<
1>
1?
0B
0D
0F
0G
b000 I
0P
0Q
0S
1T
0X
b000 Y
b000 Z
0c
0e
1g
0m
1o
0s
1t
1z
1!"
1#"
1$"
0'"
#16000000
0!
0#
0)
0+
17
18
b0001 J
b1011 K
b1011 L
b1011 M
b10110000 O
1Q
1S
b1011 [
b1011 ^
b01011 _
b01011 a
1c
1e
b0001 k
b0001 l
1m
b1011 q
b1011 r
1s
b10110000 v
0z
0{
#16500000
1!
1)
00
11
02
03
14
15
07
08
0<
1=
0>
0?
1@
1A
0Q
0S
0T
1W
0c
0e
0g
1i
0m
0o
0s
0t
1u
1z
0!"
1""
0#"
0$"
1%"
1&"
1)"
#17000000
0!
b10110000 '
0)
b10110000 .
17
18
b10110000 ;
1E
b001 I
b0110 M
b10110000 N
b01100000 O
1Q
1S
b001 Y
b001 Z
b1011 \
1]
b0110 ^
b01011 `
b10110 a
1b
1c
1e
1m
1s
b01100000 v
b10110000 x
b10110000 y
0z
#17500000
1!
b01011000 '
1)
b01011000 .
07
08
b01011000 ;
0E
b1000 J
b0000 L
b0101 M
b01011000 N
b01011000 O
0Q
0S
b0000 [
b0101 \
0]
b0101 ^
b00000 _
b00101 `
b00101 a
0b
0c
0e
0j
b1000 k
b1000 l
0m
0s
b01011000 v
b01011000 x
b01011000 y
1z
#18000000
0!
0)
17
18
b010 I
1Q
1S
b010 Y
b010 Z
1c
1e
1m
1s
0z
#18500000
1!
b00101100 '
1)
b00101100 .
07
08
b00101100 ;
b0100 J
b0010 M
b00101100 N
b00101100 O
0Q
0S
b0010 \
b0010 ^
b00010 `
b00010 a
0c
0e
b0100 k
b0100 l
0m
0s
b00101100 v
b00101100 x
b00101100 y
1z
#19000000
0!
0)
17
18
b011 I
1Q
1S
b011 Y
b011 Z
1c
1e
1m
1s
0z
#19500000
1!
b00010110 '
1)
b00010110 .
07
08
b00010110 ;
b0010 J
b0001 M
b00010110 N
b00010110 O
0Q
0S
b0001 \
b0001 ^
b00001 `
b00001 a
0c
0e
b0010 k
b0010 l
0m
0s
b00010110 v
b00010110 x
b00010110 y
1z
#20000000
0!
0)
16
17
18
1B
1D
1F
1G
b100 I
1P
1Q
1S
1X
b100 Y
b100 Z
1c
1e
1m
1s
0z
1'"
#20500000
1!
1$
b00001011 '
1)
b00001011 .
1/
01
04
05
07
08
b00001011 ;
0=
0@
0A
b0001 J
b1011 L
b1011 M
b00001011 N
b10111011 O
0Q
0S
0W
b1011 [
b0000 \
b1011 ^
b01011 _
b00000 `
b01011 a
0c
0e
0i
1j
b0001 k
b0001 l
0m
0s
0u
b10111011 v
b00001011 x
b00001011 y
1z
1}
0""
0%"
0&"
1("
0)"
#20501000
#21000000
0!
0)
06
17
18
0B
1C
0D
0G
0P
1Q
1R
1S
1c
1e
1m
1s
0z
0'"
#21500000
1!
0$
b00000101 '
1)
b00000101 .
0/
07
08
b00000101 ;
b00000101 N
b10110101 O
0Q
0S
0c
0e
0m
0s
b10110101 v
b00000101 x
b00000101 y
1z
0}
0("
#21501000
0(
#22000000
0!
0)
16
17
18
1B
0C
1D
1G
1P
1Q
0R
1S
1c
1e
1m
1s
0z
1'"
